{
    "version": "0.2.7",
    "architecture": {
        "64bit": {
            "url": "https://github.com/gechr/clover/releases/download/v0.2.7/clover_windows_amd64.zip",
            "bin": [
                "clover.exe"
            ],
            "hash": "b3ecc3768709fb6a4358b9e6f5ccd21c643e59cf77c42ac865dd0a4322dbc1f8"
        },
        "arm64": {
            "url": "https://github.com/gechr/clover/releases/download/v0.2.7/clover_windows_arm64.zip",
            "bin": [
                "clover.exe"
            ],
            "hash": "bf17b0f8cb506ef5e2b3f5bbafd5430938c088ece9de1c4605c7ccadccdf2b16"
        }
    },
    "homepage": "https://github.com/gechr/clover",
    "license": "MIT",
    "description": "Automatically manage version strings across arbitrary files"
}
