{
    "version": "0.0.14",
    "architecture": {
        "64bit": {
            "url": "https://github.com/gechr/clover/releases/download/v0.0.14/clover_windows_amd64.zip",
            "bin": [
                "clover.exe"
            ],
            "hash": "5d522610cfa3da81c681d8e7532533cc1a994d6b05c929638ddb2b1bf6529651"
        },
        "arm64": {
            "url": "https://github.com/gechr/clover/releases/download/v0.0.14/clover_windows_arm64.zip",
            "bin": [
                "clover.exe"
            ],
            "hash": "f83b7f34867951ec9d47f311928beac30025b4147bc6c4fcad306f89b26d065e"
        }
    },
    "homepage": "https://github.com/gechr/clover",
    "license": "MIT",
    "description": "Automatically manage version strings across arbitrary files"
}
